paykad/__init__.py
paykad/widgets.py
paykad-0.1.0.dist-info/METADATA
paykad-0.1.0.dist-info/WHEEL
paykad-0.1.0.dist-info/top_level.txt
paykad-0.1.0.dist-info/RECORD
