Metadata-Version: 2.1
Name: paykad
Version: 0.1.0
Summary: A simple, modern abstraction layer for Python GUI development (based on Tkinter).
Home-page: https://github.com/YourUsername/paykad
Author: Your Name
Author-email: your.email@example.com
Classifier: Programming Language :: Python :: 3
Classifier: License :: OSI Approved :: MIT License
Classifier: Operating System :: OS Independent
Classifier: Topic :: Software Development :: User Interfaces
Requires-Python: >=3.6
